[{"@odata.etag":"","ItemInternalId":"c2ecb8e2-d691-4bb5-af98-7bd43b26ec7b","Slot":"1","OE":"XXX","Contrainte":"M1","Palettes":"X"},{"@odata.etag":"","ItemInternalId":"a4df3502-a790-4d47-962d-a0d101348774","Slot":"2","OE":"XXX","Contrainte":"M2","Palettes":"X"},{"@odata.etag":"","ItemInternalId":"f1ed57ae-d236-44aa-8dbb-465479d5f6b5","Slot":"","OE":"","Contrainte":"","Palettes":""},{"@odata.etag":"","ItemInternalId":"42c2a96c-059d-4944-aa6b-4a915c367a3d","Slot":"","OE":"","Contrainte":"","Palettes":""},{"@odata.etag":"","ItemInternalId":"372f6b7d-b396-4d50-8f98-b689061c6a24","Slot":"","OE":"","Contrainte":"","Palettes":""},{"@odata.etag":"","ItemInternalId":"2e1ad3cd-efe4-47de-9787-239771fc6099","Slot":"","OE":"","Contrainte":"","Palettes":""},{"@odata.etag":"","ItemInternalId":"11228876-29ea-41ff-b833-d592d3c15616","Slot":"","OE":"","Contrainte":"","Palettes":""},{"@odata.etag":"","ItemInternalId":"01a694f4-02b9-44ed-ac50-44d8511e27e7","Slot":"","OE":"","Contrainte":"","Palettes":""},{"@odata.etag":"","ItemInternalId":"888f3639-5c5a-45d4-8fa5-1f54374174df","Slot":"","OE":"","Contrainte":"","Palettes":""},{"@odata.etag":"","ItemInternalId":"a8033a24-7779-4d64-9490-12fcbeddab4b","Slot":"","OE":"","Contrainte":"","Palettes":""}]