[{"@odata.etag":"","ItemInternalId":"6db5d582-7692-47a0-a5d9-9275832a28b1","Slot":"1","OE":"XXX","Contrainte":"M1","Palettes":"X"},{"@odata.etag":"","ItemInternalId":"7f4658ca-feb4-46d2-847e-c95ac3c2d1d5","Slot":"2","OE":"XXX","Contrainte":"M2","Palettes":"X"},{"@odata.etag":"","ItemInternalId":"a0e0cc92-ea38-45b8-bbe5-26b3bb914444","Slot":"3","OE":"XXX","Contrainte":"M3","Palettes":"X"},{"@odata.etag":"","ItemInternalId":"a56de08c-751a-41a7-8d02-6e7535218edd","Slot":"4","OE":"XXX","Contrainte":"M4","Palettes":"X"},{"@odata.etag":"","ItemInternalId":"639d4c40-2c03-491e-b602-9b33074924eb","Slot":"","OE":"","Contrainte":"","Palettes":""},{"@odata.etag":"","ItemInternalId":"44b4d268-12c8-4026-927e-777f5af9c717","Slot":"","OE":"","Contrainte":"","Palettes":""},{"@odata.etag":"","ItemInternalId":"ea95eab9-9958-4244-ad14-234d57264db1","Slot":"","OE":"","Contrainte":"","Palettes":""},{"@odata.etag":"","ItemInternalId":"2d5e4f3b-4319-4f70-9433-64f1074bc536","Slot":"","OE":"","Contrainte":"","Palettes":""},{"@odata.etag":"","ItemInternalId":"89c98cd9-c689-44ae-b9f7-472e034678c3","Slot":"","OE":"","Contrainte":"","Palettes":""},{"@odata.etag":"","ItemInternalId":"7efc2b90-b2b5-4ddf-a6d1-a49123754326","Slot":"","OE":"","Contrainte":"","Palettes":""}]