[{"@odata.etag":"","ItemInternalId":"cc7370f9-0786-4a53-bd83-88f9421d4df2","Slot":"1","OE":"XXX","Contrainte":"M1","Palettes":"X"},{"@odata.etag":"","ItemInternalId":"2b3a35c8-a165-4fed-b646-47ec0e66b568","Slot":"2","OE":"XXX","Contrainte":"M2","Palettes":"X"},{"@odata.etag":"","ItemInternalId":"cb35b2ec-8af0-474b-b415-56ae42bfd8de","Slot":"","OE":"","Contrainte":"","Palettes":""},{"@odata.etag":"","ItemInternalId":"74b82295-aea3-4956-b9c3-4754fcbb5737","Slot":"","OE":"","Contrainte":"","Palettes":""},{"@odata.etag":"","ItemInternalId":"8179d8ae-5910-4dc4-9166-b8eb5242cbf5","Slot":"","OE":"","Contrainte":"","Palettes":""},{"@odata.etag":"","ItemInternalId":"a2eab434-407d-4c81-9c9d-b61a184a3bce","Slot":"","OE":"","Contrainte":"","Palettes":""},{"@odata.etag":"","ItemInternalId":"392e06a8-3ec2-486e-98da-464166ce7368","Slot":"","OE":"","Contrainte":"","Palettes":""},{"@odata.etag":"","ItemInternalId":"9bc697a0-020b-4d10-af30-9851091c8a71","Slot":"","OE":"","Contrainte":"","Palettes":""},{"@odata.etag":"","ItemInternalId":"b5a5df6a-ce9c-4438-8f5f-c244c881fa30","Slot":"","OE":"","Contrainte":"","Palettes":""},{"@odata.etag":"","ItemInternalId":"d51e5af7-938a-4579-b0bf-030ab285c737","Slot":"","OE":"","Contrainte":"","Palettes":""}]