[{"@odata.etag":"","ItemInternalId":"64b94f39-64c1-4354-8550-574a3b5f8a85","Slot":"1","OE":"XXX","Contrainte":"M1","Palettes":"X"},{"@odata.etag":"","ItemInternalId":"6467cb08-bf37-4ce6-a879-837457cd3884","Slot":"2","OE":"XXX","Contrainte":"M2","Palettes":"X"},{"@odata.etag":"","ItemInternalId":"7dfc3500-c80b-4110-a5be-85480769c5fb","Slot":"","OE":"","Contrainte":"","Palettes":""},{"@odata.etag":"","ItemInternalId":"ea94c250-16eb-43db-9e2a-f7a2e51b8d58","Slot":"","OE":"","Contrainte":"","Palettes":""},{"@odata.etag":"","ItemInternalId":"5062797b-6880-484f-8f5c-f633646dbb1b","Slot":"","OE":"","Contrainte":"","Palettes":""},{"@odata.etag":"","ItemInternalId":"cb5146d1-e11d-4fad-893e-044520a91382","Slot":"","OE":"","Contrainte":"","Palettes":""},{"@odata.etag":"","ItemInternalId":"f4ebf494-771d-4c29-a0cf-15b126f86b87","Slot":"","OE":"","Contrainte":"","Palettes":""},{"@odata.etag":"","ItemInternalId":"5c6c93c3-254e-414c-a723-7f1f779f3705","Slot":"","OE":"","Contrainte":"","Palettes":""},{"@odata.etag":"","ItemInternalId":"df7b57a8-b270-4413-81ef-69ba8bbe7c72","Slot":"","OE":"","Contrainte":"","Palettes":""},{"@odata.etag":"","ItemInternalId":"2ac8aa27-287d-4254-8ba0-bb44e1518565","Slot":"","OE":"","Contrainte":"","Palettes":""}]