[{"@odata.etag":"","ItemInternalId":"cb3f7009-1476-4871-9940-d51a12039022","Slot":"1","OE":"XXX","Contrainte":"M1","Palettes":"X"},{"@odata.etag":"","ItemInternalId":"908134c5-3e0b-4eab-a399-7f0d85560fca","Slot":"2","OE":"XXX","Contrainte":"M2","Palettes":"X"},{"@odata.etag":"","ItemInternalId":"646aa8c3-8a1b-4f73-91f1-ee5792843dfe","Slot":"","OE":"","Contrainte":"","Palettes":""},{"@odata.etag":"","ItemInternalId":"ceb7847f-fee1-46ed-a9c5-b8825dac8ed3","Slot":"","OE":"","Contrainte":"","Palettes":""},{"@odata.etag":"","ItemInternalId":"11e5d24d-ee4b-4796-8a6e-fe4d2640ee03","Slot":"","OE":"","Contrainte":"","Palettes":""},{"@odata.etag":"","ItemInternalId":"5c595faa-8c1a-4352-a09f-9adf6b895cf2","Slot":"","OE":"","Contrainte":"","Palettes":""},{"@odata.etag":"","ItemInternalId":"9ec2cb87-3ce6-4df2-800b-88437ee6b3cf","Slot":"","OE":"","Contrainte":"","Palettes":""},{"@odata.etag":"","ItemInternalId":"07ff3f9f-f155-49e1-9b9e-0b71bae16d11","Slot":"","OE":"","Contrainte":"","Palettes":""},{"@odata.etag":"","ItemInternalId":"a3e8002a-d507-4113-bfac-14569e0a99a5","Slot":"","OE":"","Contrainte":"","Palettes":""},{"@odata.etag":"","ItemInternalId":"fb9058d8-d061-48fc-8c8e-85ae8a755077","Slot":"","OE":"","Contrainte":"","Palettes":""}]