[{"@odata.etag":"","ItemInternalId":"45227d4f-a836-495d-bc5b-ab87d93cdc25","Slot":"1","OE":"XXX","Contrainte":"M1","Palettes":"X"},{"@odata.etag":"","ItemInternalId":"a394c0b5-ab4a-4ea7-8838-e3e8b81a0a5a","Slot":"2","OE":"XXX","Contrainte":"M2","Palettes":"X"},{"@odata.etag":"","ItemInternalId":"3d8946ea-43e9-4c66-9304-45d9413ee874","Slot":"","OE":"","Contrainte":"","Palettes":""},{"@odata.etag":"","ItemInternalId":"c95391fa-8e9d-4c33-8b7d-3193ad003382","Slot":"","OE":"","Contrainte":"","Palettes":""},{"@odata.etag":"","ItemInternalId":"01c5ac34-a965-4880-a748-8fa25c683bd8","Slot":"","OE":"","Contrainte":"","Palettes":""},{"@odata.etag":"","ItemInternalId":"49ed3785-f0c7-478d-acfb-ad0460d23be7","Slot":"","OE":"","Contrainte":"","Palettes":""},{"@odata.etag":"","ItemInternalId":"d50de3ae-4548-41f7-bfd0-33c81bd95f7a","Slot":"","OE":"","Contrainte":"","Palettes":""},{"@odata.etag":"","ItemInternalId":"57ab4a22-829e-4773-949d-44820b7ed174","Slot":"","OE":"","Contrainte":"","Palettes":""},{"@odata.etag":"","ItemInternalId":"3ba90007-5d8a-4f31-b2b5-8b51c6d9bed8","Slot":"","OE":"","Contrainte":"","Palettes":""},{"@odata.etag":"","ItemInternalId":"4134a889-a471-4deb-9dd7-7476ea7c0c4d","Slot":"","OE":"","Contrainte":"","Palettes":""}]