[{"@odata.etag":"","ItemInternalId":"b5525d3d-d51b-48aa-9063-a354ed50995f","Slot":"1","OE":"XXX","Contrainte":"M1","Palettes":"X"},{"@odata.etag":"","ItemInternalId":"8d83c14e-f39e-46c5-a9de-df66b0e66819","Slot":"2","OE":"XXX","Contrainte":"M2","Palettes":"X"},{"@odata.etag":"","ItemInternalId":"84c40640-e249-4a64-8f46-842eb42fcb86","Slot":"","OE":"","Contrainte":"","Palettes":""},{"@odata.etag":"","ItemInternalId":"e5faa137-8335-4854-ba06-9ce883752f1a","Slot":"","OE":"","Contrainte":"","Palettes":""},{"@odata.etag":"","ItemInternalId":"5085adc4-aa3c-43ef-b2cb-797cab863eac","Slot":"","OE":"","Contrainte":"","Palettes":""},{"@odata.etag":"","ItemInternalId":"fd180ec6-c805-4535-b486-534083767d6b","Slot":"","OE":"","Contrainte":"","Palettes":""},{"@odata.etag":"","ItemInternalId":"0a72638e-0d4b-4d61-a42f-0c5833654b9b","Slot":"","OE":"","Contrainte":"","Palettes":""},{"@odata.etag":"","ItemInternalId":"a788acf2-9111-47b7-82b3-c2792bcbc933","Slot":"","OE":"","Contrainte":"","Palettes":""},{"@odata.etag":"","ItemInternalId":"7fea1cab-25bf-46ed-b9ab-e58e818647a8","Slot":"","OE":"","Contrainte":"","Palettes":""},{"@odata.etag":"","ItemInternalId":"66866a3d-bcaf-40d5-9b2d-60020c592b47","Slot":"","OE":"","Contrainte":"","Palettes":""}]