[{"@odata.etag":"","ItemInternalId":"f0888595-484e-49de-a77a-357d2a6d0c9f","Slot":"1","OE":"XXX","Contrainte":"M1","Palettes":"X"},{"@odata.etag":"","ItemInternalId":"e221aba9-fe4a-48ce-a34c-cd7860ec165e","Slot":"2","OE":"XXX","Contrainte":"M2","Palettes":"X"},{"@odata.etag":"","ItemInternalId":"8fd6c3e4-6b32-4035-9afc-f9f104fed56c","Slot":"","OE":"","Contrainte":"","Palettes":""},{"@odata.etag":"","ItemInternalId":"7d282cc5-32c6-4358-8358-759cd1da7be4","Slot":"","OE":"","Contrainte":"","Palettes":""},{"@odata.etag":"","ItemInternalId":"4ed475a2-d597-4307-bb4e-73345c0713d1","Slot":"","OE":"","Contrainte":"","Palettes":""},{"@odata.etag":"","ItemInternalId":"3912a718-ad70-4f6e-b533-45dc66995bcd","Slot":"","OE":"","Contrainte":"","Palettes":""},{"@odata.etag":"","ItemInternalId":"2873fa61-a227-489c-9a79-e17c8cb99609","Slot":"","OE":"","Contrainte":"","Palettes":""},{"@odata.etag":"","ItemInternalId":"7495fdb9-1352-417f-b768-3ae9bc72cb6a","Slot":"","OE":"","Contrainte":"","Palettes":""},{"@odata.etag":"","ItemInternalId":"8513cdef-1654-4512-984c-f42ba96da2f4","Slot":"","OE":"","Contrainte":"","Palettes":""},{"@odata.etag":"","ItemInternalId":"9daf45a6-da97-4c9a-abb6-78ee6f63dd71","Slot":"","OE":"","Contrainte":"","Palettes":""}]