[{"@odata.etag":"","ItemInternalId":"1349bb9d-f992-4c14-bf16-232d0ebe4c0b","Slot":"1","OE":"XXX","Contrainte":"M1","Palettes":"X"},{"@odata.etag":"","ItemInternalId":"285bd035-2376-431b-88ff-0aebeef0990c","Slot":"2","OE":"XXX","Contrainte":"M2","Palettes":"X"},{"@odata.etag":"","ItemInternalId":"3ba737e9-9c7c-4d24-8d92-ad3db995390a","Slot":"3","OE":"XXX","Contrainte":"M3","Palettes":"X"},{"@odata.etag":"","ItemInternalId":"49b77dea-3ec2-413c-a171-7171e611f3f8","Slot":"4","OE":"XXX","Contrainte":"M4","Palettes":"X"},{"@odata.etag":"","ItemInternalId":"57e5694d-d2c4-4278-8095-722966691ae7","Slot":"5","OE":"XXX","Contrainte":"M5","Palettes":"X"},{"@odata.etag":"","ItemInternalId":"c585df88-557f-428c-bc80-0a88ecf7de80","Slot":"6","OE":"XXX","Contrainte":"M6","Palettes":"X"},{"@odata.etag":"","ItemInternalId":"5162d780-7523-4417-adb2-07f8f1ddb144","Slot":"7","OE":"XXX","Contrainte":"M7","Palettes":"X"},{"@odata.etag":"","ItemInternalId":"7596c054-8f2e-4fd2-9048-5aac8db0701d","Slot":"","OE":"","Contrainte":"","Palettes":""},{"@odata.etag":"","ItemInternalId":"d812a7ab-9366-4a5c-a23a-0cf8dac32169","Slot":"","OE":"","Contrainte":"","Palettes":""},{"@odata.etag":"","ItemInternalId":"e1d2a696-9f9d-4e29-8860-7139aa015c97","Slot":"","OE":"","Contrainte":"","Palettes":""}]