[{"@odata.etag":"","ItemInternalId":"f504a921-4124-4ada-9174-ac9cfd9ebda2","Slot":"1","OE":"XXX","Contrainte":"M1","Palettes":"X"},{"@odata.etag":"","ItemInternalId":"fcb23af7-d10f-4812-80a3-aee6f046d4c7","Slot":"2","OE":"XXX","Contrainte":"M2","Palettes":"X"},{"@odata.etag":"","ItemInternalId":"2392abd4-0f6b-4eca-96b0-66d879be6ec4","Slot":"3","OE":"XXX","Contrainte":"M3","Palettes":"X"},{"@odata.etag":"","ItemInternalId":"eddb75b8-18e9-48f2-93e7-62ed9cfe591a","Slot":"4","OE":"XXX","Contrainte":"M4","Palettes":"X"},{"@odata.etag":"","ItemInternalId":"2349c7a0-fb9c-481c-9ede-dced9b3344ed","Slot":"5","OE":"XXX","Contrainte":"M5","Palettes":"X"},{"@odata.etag":"","ItemInternalId":"57ef125f-3f87-4005-9c59-0084bf9f92e8","Slot":"","OE":"","Contrainte":"","Palettes":""},{"@odata.etag":"","ItemInternalId":"addd6afa-3dbd-46a9-b9d4-d2115134193a","Slot":"","OE":"","Contrainte":"","Palettes":""},{"@odata.etag":"","ItemInternalId":"b4cf68bb-d8da-441d-881b-b6dc705a8606","Slot":"","OE":"","Contrainte":"","Palettes":""},{"@odata.etag":"","ItemInternalId":"af314d34-d40a-46e0-b384-a9dd9e02e53c","Slot":"","OE":"","Contrainte":"","Palettes":""},{"@odata.etag":"","ItemInternalId":"e15cf7f1-9d8e-4db3-8ea3-c69b665ad566","Slot":"","OE":"","Contrainte":"","Palettes":""}]