[{"@odata.etag":"","ItemInternalId":"d4a98bdd-e91d-4f20-85ec-7cd7663edbd6","Slot":"1","OE":"XXX","Contrainte":"M1","Palettes":"X"},{"@odata.etag":"","ItemInternalId":"801680b4-0ead-41b2-8f43-001ee0a526dc","Slot":"2","OE":"XXX","Contrainte":"M2","Palettes":"X"},{"@odata.etag":"","ItemInternalId":"a96ff8ef-853f-43f1-af6f-9faf4b6d75a0","Slot":"3","OE":"XXX","Contrainte":"M3","Palettes":"X"},{"@odata.etag":"","ItemInternalId":"3015d57a-aee3-48c8-a34c-fb90131d2bc1","Slot":"4","OE":"XXX","Contrainte":"M4","Palettes":"X"},{"@odata.etag":"","ItemInternalId":"f566c773-49bd-46c7-aa8c-2d51061c5ea2","Slot":"","OE":"","Contrainte":"","Palettes":""},{"@odata.etag":"","ItemInternalId":"063c259c-fcb2-41f8-930f-10dcf8099aec","Slot":"","OE":"","Contrainte":"","Palettes":""},{"@odata.etag":"","ItemInternalId":"5dd68c6b-4e64-486a-b2bf-513b5fbdb4e9","Slot":"","OE":"","Contrainte":"","Palettes":""},{"@odata.etag":"","ItemInternalId":"e176586e-1b53-409e-8a9b-03dfd17ef9c1","Slot":"","OE":"","Contrainte":"","Palettes":""},{"@odata.etag":"","ItemInternalId":"96833568-8470-45ab-9cf5-6280e91f94e1","Slot":"","OE":"","Contrainte":"","Palettes":""},{"@odata.etag":"","ItemInternalId":"9cead222-f7c5-46c2-9cfc-0e5e3a2ca1b9","Slot":"","OE":"","Contrainte":"","Palettes":""}]