[{"@odata.etag":"","ItemInternalId":"1dd8b9fb-ffea-412c-a06b-804b89398c73","Slot":"1","OE":"XXX","Contrainte":"M1","Palettes":"X"},{"@odata.etag":"","ItemInternalId":"d920cfc6-d44b-4d51-9016-527da31e32dc","Slot":"2","OE":"XXX","Contrainte":"M2","Palettes":"X"},{"@odata.etag":"","ItemInternalId":"afd80d0e-c4e0-4bd6-9731-156e475c36de","Slot":"3","OE":"XXX","Contrainte":"M3","Palettes":"X"},{"@odata.etag":"","ItemInternalId":"c7bdc388-8aff-45f3-b9a8-da8347579f11","Slot":"4","OE":"XXX","Contrainte":"M4","Palettes":"X"},{"@odata.etag":"","ItemInternalId":"f0d42b30-35dc-47de-9169-545ede343806","Slot":"","OE":"","Contrainte":"","Palettes":""},{"@odata.etag":"","ItemInternalId":"3bc70378-672c-4d88-a20e-a713440261d7","Slot":"","OE":"","Contrainte":"","Palettes":""},{"@odata.etag":"","ItemInternalId":"8dbdbad6-86cf-44bc-95d9-b72cf2f40a33","Slot":"","OE":"","Contrainte":"","Palettes":""},{"@odata.etag":"","ItemInternalId":"2bb99e2e-b4aa-46c3-89e2-6356b2e6776f","Slot":"","OE":"","Contrainte":"","Palettes":""},{"@odata.etag":"","ItemInternalId":"2074973a-4546-428f-936f-d250a86e1e6f","Slot":"","OE":"","Contrainte":"","Palettes":""},{"@odata.etag":"","ItemInternalId":"0b1d7261-014a-4af1-bbeb-124aa94c0791","Slot":"","OE":"","Contrainte":"","Palettes":""}]